pylangdb/__init__.py
pylangdb/feature_flags.py
pylangdb/adk/__init__.py
pylangdb/adk/agent.py
pylangdb/adk/langdb_llm.py
pylangdb/adk/tracing.py
pylangdb/agno/__init__.py
pylangdb/agno/tracing.py
pylangdb/client/__init__.py
pylangdb/client/client.py
pylangdb/client/types.py
pylangdb/core/__init__.py
pylangdb/core/tracing.py
pylangdb/crewai/__init__.py
pylangdb/crewai/tracing.py
pylangdb/langchain/__init__.py
pylangdb/langchain/tracing.py
pylangdb/openai/__init__.py
pylangdb/openai/tracing.py
pylangdb-0.3.6.dist-info/licenses/LICENSE
pylangdb-0.3.6.dist-info/METADATA
pylangdb-0.3.6.dist-info/WHEEL
pylangdb-0.3.6.dist-info/top_level.txt
pylangdb-0.3.6.dist-info/RECORD
