Metadata-Version: 2.4
Name: pylangdb
Version: 0.3.6
Summary: Comprehensive LangDB integration package with enhanced agent support, LLM integration, and distributed tracing.
Requires-Python: >=3.10
License-File: LICENSE
Requires-Dist: opentelemetry-api>=1.18.0
Requires-Dist: opentelemetry-sdk>=1.18.0
Requires-Dist: opentelemetry-exporter-otlp>=1.18.0
Requires-Dist: uuid>=1.0.0
Provides-Extra: adk
Requires-Dist: google-adk>=1.5.0; extra == "adk"
Provides-Extra: agno
Requires-Dist: agno>=1.7.0; extra == "agno"
Requires-Dist: openinference-instrumentation-agno>=0.1.7; extra == "agno"
Provides-Extra: crewai
Requires-Dist: openinference-instrumentation-crewai>=0.1.10; extra == "crewai"
Requires-Dist: litellm>=1.72.0; extra == "crewai"
Provides-Extra: langchain
Requires-Dist: openinference-instrumentation-langchain>=0.1.7; extra == "langchain"
Provides-Extra: openai
Requires-Dist: openai>=1.60.2; extra == "openai"
Requires-Dist: openinference-instrumentation-openai-agents>=0.1.14; extra == "openai"
Provides-Extra: client
Requires-Dist: pandas>=2.2.2; extra == "client"
Requires-Dist: requests>=2.32.3; extra == "client"
Requires-Dist: openai>=1.60.2; extra == "client"
Requires-Dist: python-dotenv>=1.0.1; extra == "client"
Provides-Extra: all
Requires-Dist: agno>=1.7.0; extra == "all"
Requires-Dist: google-adk>=1.3.0; extra == "all"
Requires-Dist: litellm>=1.72.0; extra == "all"
Requires-Dist: openai>=1.60.2; extra == "all"
Requires-Dist: opentelemetry-instrumentation-openai-agents>=0.1.14; extra == "all"
Requires-Dist: openinference-instrumentation-agno>=0.1.7; extra == "all"
Requires-Dist: openinference-instrumentation-crewai>=0.1.10; extra == "all"
Requires-Dist: openinference-instrumentation-langchain>=0.1.7; extra == "all"
Dynamic: license-file
